unbias/__init__.py
unbias/main.py
unbias/data/lexicons.txt
UnBIASing-1.0.dist-info/License.txt
UnBIASing-1.0.dist-info/METADATA
UnBIASing-1.0.dist-info/WHEEL
UnBIASing-1.0.dist-info/top_level.txt
UnBIASing-1.0.dist-info/RECORD
