Metadata-Version: 2.1
Name: UnBIASing
Version: 1.0
Summary: A package to detect and debias text using pretrained models
Home-page: https://github.com/your_github_username/UnBIASing
Author: Shaina Raza
Author-email: shaina.raza@utoronto.ca
Classifier: Programming Language :: Python :: 3
Classifier: License :: OSI Approved :: MIT License
Classifier: Operating System :: OS Independent
License-File: License.txt
Requires-Dist: pandas
Requires-Dist: transformers
Requires-Dist: torch
Requires-Dist: sentencepiece
